prepnet/__init__.py
prepnet/version.py
prepnet/category/__init__.py
prepnet/category/onehot_converter.py
prepnet/category/ordinal_converter.py
prepnet/core/__init__.py
prepnet/core/astype_converter.py
prepnet/core/column_converter_base.py
prepnet/core/config.py
prepnet/core/converter_reference.py
prepnet/core/dataframe_array.py
prepnet/core/frame_converter_base.py
prepnet/core/frame_converter_context.py
prepnet/core/lambda_converter.py
prepnet/core/module.py
prepnet/core/null_converter.py
prepnet/core/sequence_converter.py
prepnet/executor/__init__.py
prepnet/executor/column_executor.py
prepnet/executor/conversion_plan.py
prepnet/executor/converter_array.py
prepnet/executor/exec_mode.py
prepnet/executor/executor.py
prepnet/executor/executor_base.py
prepnet/executor/frame_executor.py
prepnet/executor/state_manager.py
prepnet/executor/state_value.py
prepnet/extra/__init__.py
prepnet/extra/split_converter.py
prepnet/functional/__init__.py
prepnet/functional/column_context.py
prepnet/functional/configuration_context.py
prepnet/functional/configuration_context_base.py
prepnet/functional/converter_array.py
prepnet/functional/fixed_stage.py
prepnet/functional/frame_context.py
prepnet/functional/function_configuration.py
prepnet/functional/functional_context.py
prepnet/functional/registry.py
prepnet/impute/drop_na.py
prepnet/impute/fill_na.py
prepnet/impute/nan_imputer.py
prepnet/math/__init__.py
prepnet/math/exp_transform.py
prepnet/math/log_transform.py
prepnet/normalize/__init__.py
prepnet/normalize/quantile_normalize.py
prepnet/normalize/quantile_round.py
prepnet/normalize/standardize.py
prepnet/time/__init__.py
prepnet/time/frequency_time.py
prepnet-0.2.0.dist-info/LICENSE
prepnet-0.2.0.dist-info/METADATA
prepnet-0.2.0.dist-info/WHEEL
prepnet-0.2.0.dist-info/top_level.txt
prepnet-0.2.0.dist-info/RECORD
